debounce/__init__.py
debounce/aio.py
py_debounce-0.1.2.dist-info/METADATA
py_debounce-0.1.2.dist-info/WHEEL
py_debounce-0.1.2.dist-info/licenses/LICENSE
py_debounce-0.1.2.dist-info/RECORD
