Metadata-Version: 2.4
Name: py-debounce
Version: 0.1.2
Summary: Python implementation of debounce functionality.
License-File: LICENSE
Requires-Python: >=3.7
